gevent/resolver_ares.py
gevent/subprocess.py
gevent/_gevent_c_greenlet_primitives.cpython-36m-x86_64-linux-gnu.so
gevent/ares.py
gevent/threadpool.py
gevent/_gevent_c_semaphore.cpython-36m-x86_64-linux-gnu.so
gevent/_gevent_cevent.cpython-36m-x86_64-linux-gnu.so
gevent/_hub_local.py
gevent/_ident.py
gevent/_compat.py
gevent/_fileobjectposix.py
gevent/greenlet.py
gevent/lock.py
gevent/selectors.py
gevent/signal.py
gevent/time.py
gevent/contextvars.py
gevent/_gevent_c_imap.cpython-36m-x86_64-linux-gnu.so
gevent/_gevent_c_hub_primitives.cpython-36m-x86_64-linux-gnu.so
gevent/_tblib.py
gevent/builtins.py
gevent/_tracer.py
gevent/_config.py
gevent/_patcher.py
gevent/_abstract_linkable.py
gevent/baseserver.py
gevent/_hub_primitives.py
gevent/pywsgi.py
gevent/_waiter.py
gevent/_sslgte279.py
gevent/_gevent_clocal.cpython-36m-x86_64-linux-gnu.so
gevent/_socket3.py
gevent/_socket2.py
gevent/_fileobjectcommon.py
gevent/_socketcommon.py
gevent/server.py
gevent/exceptions.py
gevent/_gevent_cqueue.cpython-36m-x86_64-linux-gnu.so
gevent/select.py
gevent/_threading.py
gevent/_gevent_c_waiter.cpython-36m-x86_64-linux-gnu.so
gevent/core.py
gevent/fileobject.py
gevent/util.py
gevent/backdoor.py
gevent/local.py
gevent/_gevent_c_ident.cpython-36m-x86_64-linux-gnu.so
gevent/_gevent_c_hub_local.cpython-36m-x86_64-linux-gnu.so
gevent/_gevent_c_abstract_linkable.cpython-36m-x86_64-linux-gnu.so
gevent/_gevent_cgreenlet.cpython-36m-x86_64-linux-gnu.so
gevent/_util_py2.py
gevent/hub.py
gevent/_util.py
gevent/_gevent_c_tracer.cpython-36m-x86_64-linux-gnu.so
gevent/event.py
gevent/_greenlet_primitives.py
gevent/_ssl3.py
gevent/os.py
gevent/_imap.py
gevent/monkey.py
gevent/queue.py
gevent/threading.py
gevent/__init__.py
gevent/pool.py
gevent/_monitor.py
gevent/_interfaces.py
gevent/_ssl2.py
gevent/_semaphore.py
gevent/win32util.py
gevent/socket.py
gevent/resolver_thread.py
gevent/thread.py
gevent/events.py
levoai_gevent-21.12.1.dev0.dist-info/LICENSE
levoai_gevent-21.12.1.dev0.dist-info/METADATA
levoai_gevent-21.12.1.dev0.dist-info/top_level.txt
levoai_gevent-21.12.1.dev0.dist-info/RECORD
levoai_gevent-21.12.1.dev0.dist-info/entry_points.txt
levoai_gevent-21.12.1.dev0.dist-info/WHEEL
levoai_gevent-21.12.1.dev0.dist-info/NOTICE
levoai_gevent-21.12.1.dev0.dist-info/AUTHORS
