Metadata-Version: 2.1
Name: levoai-gevent
Version: 21.12.1.dev0
Summary: Coroutine-based network library
Home-page: http://www.gevent.org/
Author: Denis Bilenko
Author-email: denis.bilenko@gmail.com
Maintainer: Jason Madden
Maintainer-email: jason@nextthought.com
License: MIT
Project-URL: Bug Tracker, https://github.com/gevent/gevent/issues
Project-URL: Source Code, https://github.com/gevent/gevent/
Project-URL: Documentation, http://www.gevent.org
Keywords: greenlet coroutine cooperative multitasking light threads monkey
Platform: UNKNOWN
Classifier: License :: OSI Approved :: MIT License
Classifier: Programming Language :: Python :: 2.7
Classifier: Programming Language :: Python :: 3.6
Classifier: Programming Language :: Python :: 3.7
Classifier: Programming Language :: Python :: 3.8
Classifier: Programming Language :: Python :: 3.9
Classifier: Programming Language :: Python :: 3.10
Classifier: Programming Language :: Python :: Implementation :: CPython
Classifier: Programming Language :: Python :: Implementation :: PyPy
Classifier: Operating System :: MacOS :: MacOS X
Classifier: Operating System :: POSIX
Classifier: Operating System :: Microsoft :: Windows
Classifier: Topic :: Internet
Classifier: Topic :: Software Development :: Libraries :: Python Modules
Classifier: Intended Audience :: Developers
Classifier: Development Status :: 4 - Beta
Requires-Python: >=2.7,!=3.0.*,!=3.1.*,!=3.2.*,!=3.3.*,!=3.4.*,!=3.5
License-File: LICENSE
License-File: NOTICE
License-File: AUTHORS
Requires-Dist: zope.event
Requires-Dist: zope.interface
Requires-Dist: setuptools
Requires-Dist: greenlet (<2.0,>=1.1.0) ; platform_python_implementation == "CPython"
Requires-Dist: cffi (>=1.12.2) ; platform_python_implementation == "CPython" and sys_platform == "win32"
Provides-Extra: dnspython
Requires-Dist: dnspython (<2.0,>=1.16.0) ; (python_version < "3.10") and extra == 'dnspython'
Requires-Dist: idna ; (python_version < "3.10") and extra == 'dnspython'
Provides-Extra: docs
Requires-Dist: repoze.sphinx.autointerface ; extra == 'docs'
Requires-Dist: sphinxcontrib-programoutput ; extra == 'docs'
Requires-Dist: zope.schema ; extra == 'docs'
Provides-Extra: events
Provides-Extra: monitor
Requires-Dist: psutil (>=5.7.0) ; (sys_platform != "win32" or platform_python_implementation == "CPython") and extra == 'monitor'
Provides-Extra: recommended
Requires-Dist: cffi (>=1.12.2) ; (platform_python_implementation == "CPython") and extra == 'recommended'
Requires-Dist: dnspython (<2.0,>=1.16.0) ; (python_version < "3.10") and extra == 'recommended'
Requires-Dist: idna ; (python_version < "3.10") and extra == 'recommended'
Requires-Dist: selectors2 ; (python_version == "2.7") and extra == 'recommended'
Requires-Dist: backports.socketpair ; (python_version == "2.7" and sys_platform == "win32") and extra == 'recommended'
Requires-Dist: psutil (>=5.7.0) ; (sys_platform != "win32" or platform_python_implementation == "CPython") and extra == 'recommended'
Provides-Extra: test
Requires-Dist: requests ; extra == 'test'
Requires-Dist: objgraph ; extra == 'test'
Requires-Dist: cffi (>=1.12.2) ; (platform_python_implementation == "CPython") and extra == 'test'
Requires-Dist: dnspython (<2.0,>=1.16.0) ; (python_version < "3.10") and extra == 'test'
Requires-Dist: idna ; (python_version < "3.10") and extra == 'test'
Requires-Dist: selectors2 ; (python_version == "2.7") and extra == 'test'
Requires-Dist: futures ; (python_version == "2.7") and extra == 'test'
Requires-Dist: mock ; (python_version == "2.7") and extra == 'test'
Requires-Dist: backports.socketpair ; (python_version == "2.7" and sys_platform == "win32") and extra == 'test'
Requires-Dist: contextvars (==2.4) ; (python_version > "3.0" and python_version < "3.7") and extra == 'test'
Requires-Dist: coverage (>=5.0) ; (sys_platform != "win32") and extra == 'test'
Requires-Dist: coveralls (>=1.7.0) ; (sys_platform != "win32") and extra == 'test'
Requires-Dist: psutil (>=5.7.0) ; (sys_platform != "win32" or platform_python_implementation == "CPython") and extra == 'test'
